plotlp/__init__.py
plotlp/modules/StyledAxes_LP/StyledAxes.py
plotlp/modules/StyledAxes_LP/__init__.py
plotlp/modules/StyledAxes_LP/functions/__init__.py
plotlp/modules/StyledAxes_LP/functions/__template__.py
plotlp/modules/StyledAxes_LP/test_StyledAxes.py
plotlp/modules/StyledFigure_LP/StyledFigure.py
plotlp/modules/StyledFigure_LP/__init__.py
plotlp/modules/StyledFigure_LP/functions/__init__.py
plotlp/modules/StyledFigure_LP/functions/__template__.py
plotlp/modules/StyledFigure_LP/test_StyledFigure.py
plotlp/modules/__init__.py
plotlp/modules/cmap_LP/__init__.py
plotlp/modules/cmap_LP/cmap.py
plotlp/modules/cmap_LP/functions/__init__.py
plotlp/modules/cmap_LP/functions/__template__.py
plotlp/modules/cmap_LP/test_cmap.py
plotlp/modules/color_LP/__init__.py
plotlp/modules/color_LP/color.py
plotlp/modules/color_LP/functions/__init__.py
plotlp/modules/color_LP/functions/__template__.py
plotlp/modules/color_LP/test_color.py
plotlp/modules/figure_LP/__init__.py
plotlp/modules/figure_LP/figure.py
plotlp/modules/figure_LP/functions/__init__.py
plotlp/modules/figure_LP/functions/__template__.py
plotlp/modules/figure_LP/test_figure.py
plotlp/modules/imgfigure_LP/__init__.py
plotlp/modules/imgfigure_LP/functions/__init__.py
plotlp/modules/imgfigure_LP/functions/__template__.py
plotlp/modules/imgfigure_LP/imgfigure.py
plotlp/modules/imgfigure_LP/test_imgfigure.py
plotlp/modules/plt_LP/__init__.py
plotlp/modules/plt_LP/functions/__init__.py
plotlp/modules/plt_LP/functions/__template__.py
plotlp/modules/plt_LP/plt.py
plotlp/modules/plt_LP/test_plt.py
plotlp/modules/style_LP/__init__.py
plotlp/modules/style_LP/functions/__init__.py
plotlp/modules/style_LP/functions/__template__.py
plotlp/modules/style_LP/style.py
plotlp/modules/style_LP/styles/__init__.py
plotlp/modules/style_LP/styles/darkLP.py
plotlp/modules/style_LP/styles/default.py
plotlp/modules/style_LP/styles/lightLP.py
plotlp/modules/style_LP/styles/styleLP.py
plotlp/modules/style_LP/test_style.py
plotlp-0.1.8.dist-info/WHEEL
plotlp-0.1.8.dist-info/METADATA
plotlp-0.1.8.dist-info/RECORD
