Metadata-Version: 2.3
Name: plotlp
Version: 0.1.8
Summary: A library wrapper around matplotlib for custom plots.
Requires-Dist: corelp
Requires-Dist: cycler
Requires-Dist: matplotlib
Requires-Dist: numpy
Requires-Dist: pillow
Requires-Python: >=3.12
